tilt_mcp/__init__.py
tilt_mcp/py.typed
tilt_mcp/server.py
tilt_mcp-0.1.3.dist-info/licenses/LICENSE
tilt_mcp-0.1.3.dist-info/METADATA
tilt_mcp-0.1.3.dist-info/WHEEL
tilt_mcp-0.1.3.dist-info/entry_points.txt
tilt_mcp-0.1.3.dist-info/top_level.txt
tilt_mcp-0.1.3.dist-info/RECORD
