Metadata-Version: 2.4
Name: tilt-mcp
Version: 0.1.3
Summary: Model Context Protocol server for Tilt - interact with Tilt resources through MCP
Author-email: Aryan Agrawal <aryan.agrawal@glean.com>
License: MIT
Project-URL: Homepage, https://github.com/aryan-agrawal-glean/tilt-mcp
Project-URL: Bug Tracker, https://github.com/aryan-agrawal-glean/tilt-mcp/issues
Project-URL: Documentation, https://github.com/aryan-agrawal-glean/tilt-mcp#readme
Keywords: mcp,tilt,kubernetes,development,model-context-protocol
Classifier: Development Status :: 3 - Alpha
Classifier: Intended Audience :: Developers
Classifier: Topic :: Software Development :: Build Tools
Classifier: Topic :: Software Development :: Libraries :: Python Modules
Classifier: License :: OSI Approved :: MIT License
Classifier: Programming Language :: Python :: 3
Classifier: Programming Language :: Python :: 3.8
Classifier: Programming Language :: Python :: 3.9
Classifier: Programming Language :: Python :: 3.10
Classifier: Programming Language :: Python :: 3.11
Classifier: Programming Language :: Python :: 3.12
Requires-Python: >=3.8
License-File: LICENSE
Requires-Dist: fastmcp>=0.1.0
Provides-Extra: dev
Requires-Dist: pytest>=7.0; extra == "dev"
Requires-Dist: pytest-asyncio>=0.21.0; extra == "dev"
Requires-Dist: pytest-cov>=4.0; extra == "dev"
Requires-Dist: black>=23.0; extra == "dev"
Requires-Dist: ruff>=0.1.0; extra == "dev"
Requires-Dist: mypy>=1.0; extra == "dev"
Dynamic: license-file
